DocClasses/ST_docs.py
DocClasses/__init__.py
DocClasses/run.py
DocClasses/templates/pou_md_doc_template.txt
gen/StructuredText.interp
gen/StructuredText.tokens
gen/StructuredTextLexer.interp
gen/StructuredTextLexer.py
gen/StructuredTextLexer.tokens
gen/StructuredTextListener.py
gen/StructuredTextParser.py
gen/__init__.py
twincat_doc/__init__.py
twincat_doc/plugin.py
mkdocs_twincat_doc_plugin-0.0.15.dist-info/LICENSE
mkdocs_twincat_doc_plugin-0.0.15.dist-info/METADATA
mkdocs_twincat_doc_plugin-0.0.15.dist-info/WHEEL
mkdocs_twincat_doc_plugin-0.0.15.dist-info/entry_points.txt
mkdocs_twincat_doc_plugin-0.0.15.dist-info/top_level.txt
mkdocs_twincat_doc_plugin-0.0.15.dist-info/RECORD
